normalize_lists/LICENSE
normalize_lists/README.MD
normalize_lists/__init__.py
normalize_lists/requirements.txt
normalize_lists/thirdparty.json
normalize_lists-0.10.dist-info/LICENSE.rst
normalize_lists-0.10.dist-info/METADATA
normalize_lists-0.10.dist-info/WHEEL
normalize_lists-0.10.dist-info/top_level.txt
normalize_lists-0.10.dist-info/RECORD
